{"pageContext":{"slug":"/blog/photoshop-compositing-basics-stockfotos","left":{"frontmatter":{"tags":["Gatsby","Gatsby-Starter"],"category":"Coding","title":"Gatsby Starter Portfolio","cover":{"childImageSharp":{"resize":{"src":"/static/gatsby_starter_portfolio-d4da4203ecbce8c093f317d78b4a9e77-735d8.jpg"}}}},"fields":{"slug":"/blog/gatsby-starter-portfolio"}},"right":{"frontmatter":{"tags":["Netlify","Discord"],"category":"Quicktipp","title":"Quicktipp: Netlify + Discord","cover":{"childImageSharp":{"resize":{"src":"/static/netlify-and-discord-1c11979b664a737c4d748b895d4507a7-735d8.jpg"}}}},"fields":{"slug":"/blog/quicktipp-netlify-discord"}}}}