{"pageContext":{"slug":"/blog/gatsby-js","left":{"frontmatter":{"tags":["Weihnachten"],"category":"Freebie","title":"Frohe Weihnachten","cover":{"childImageSharp":{"resize":{"src":"/static/Frohe_Weihnachten_2017-ad65d9f3cb8b8c2211a018bb18af65c0-735d8.jpg"}}}},"fields":{"slug":"/blog/frohe-weihnachten"}},"right":{"frontmatter":{"tags":["Gatsby","Gatsby-Starter"],"category":"Coding","title":"Gatsby Starter Portfolio","cover":{"childImageSharp":{"resize":{"src":"/static/gatsby_starter_portfolio-d4da4203ecbce8c093f317d78b4a9e77-735d8.jpg"}}}},"fields":{"slug":"/blog/gatsby-starter-portfolio"}}}}